README.md
setup.py
rasa_d/__init__.py
rasa_d/__main__.py
rasa_d/main.py
rasa_d/rasa_commands.py
rasa_d/tunnel_commands.py
rasa_d.egg-info/PKG-INFO
rasa_d.egg-info/SOURCES.txt
rasa_d.egg-info/dependency_links.txt
rasa_d.egg-info/entry_points.txt
rasa_d.egg-info/requires.txt
rasa_d.egg-info/top_level.txt